SequenceTool/SeqProcessingTool.py
SequenceTool/__init__.py
SequenceTool/amino_count.py
SequenceTool/barcode.py
SequenceTool/dna2aa.py
sequence_processing_tool-0.1.0.dist-info/licenses/LICENSE
sequence_processing_tool-0.1.0.dist-info/METADATA
sequence_processing_tool-0.1.0.dist-info/WHEEL
sequence_processing_tool-0.1.0.dist-info/top_level.txt
sequence_processing_tool-0.1.0.dist-info/RECORD
