Metadata-Version: 2.4
Name: sequence-processing-tool
Version: 0.1.0
Summary: A simple sequence processing tool with utility scripts.
Author: Yaqi Jiao
License: MIT License
Project-URL: Homepage, https://github.com/yaqi-jiao/SeqProcessingTool
Requires-Python: >=3.8
License-File: LICENSE
Dynamic: license-file
